[
    {
      "fileName": "GATE_CS_1996.csv",
      "questionNumber": "1",
      "subject": "Operating System",
      "chapter": "Core Concepts",
      "subtopic": "System calls, processes, threads"
    },
    {
      "fileName": "GATE_CS_1996.csv",
      "questionNumber": "2",
      "subject": "Algorithms",
      "chapter": "Basic Techniques",
      "subtopic": "Searching, sorting, hashing"
    },
    {
      "fileName": "GATE_CS_1996.csv",
      "questionNumber": "3",
      "subject": null,
      "chapter": null,
      "subtopic": null
    },
    {
      "fileName": "GATE_CS_1996.csv",
      "questionNumber": "4",
      "subject": "Programming and Data Structures",
      "chapter": "Linear Data Structures",
      "subtopic": "Arrays, stacks, queues, linked lists"
    },
    {
      "fileName": "GATE_CS_1996.csv",
      "questionNumber": "5",
      "subject": "Algorithms",
      "chapter": "Graph Algorithms",
      "subtopic": "Graph traversals, minimum spanning trees, shortest paths"
    },
    {
      "fileName": "GATE_CS_1996.csv",
      "questionNumber": "6",
      "subject": "Algorithms",
      "chapter": "Basic Techniques",
      "subtopic": "Searching, sorting, hashing"
    },
    {
      "fileName": "GATE_CS_1996.csv",
      "questionNumber": "7",
      "subject": "Algorithms",
      "chapter": "Graph Algorithms",
      "subtopic": "Graph traversals, minimum spanning trees, shortest paths"
    },
    {
      "fileName": "GATE_CS_1996.csv",
      "questionNumber": "8",
      "subject": "Operating System",
      "chapter": "Memory Management",
      "subtopic": "Memory management and virtual memory"
    },
    {
      "fileName": "GATE_CS_1996.csv",
      "questionNumber": "9",
      "subject": "Operating System",
      "chapter": "Memory Management",
      "subtopic": "Memory management and virtual memory"
    },
    {
      "fileName": "GATE_CS_1996.csv",
      "questionNumber": "10",
      "subject": "Compiler Design",
      "chapter": "Runtime Environments",
      "subtopic": null
    },
    {
      "fileName": "GATE_CS_1996.csv",
      "questionNumber": "11",
      "subject": "Operating System",
      "chapter": "Concurrency",
      "subtopic": "Inter-process communication, concurrency and synchronization, Deadlock"
    },
    {
      "fileName": "GATE_CS_1996.csv",
      "questionNumber": "12",
      "subject": "Computer Organization and Architecture",
      "chapter": "Input/Output (I/O)",
      "subtopic": "I/O interface (interrupt and DMA mode)"
    },
    {
      "fileName": "GATE_CS_1996.csv",
      "questionNumber": "13",
      "subject": "Operating System",
      "chapter": "File Systems",
      "subtopic": null
    },
    {
      "fileName": "GATE_CS_1996.csv",
      "questionNumber": "14",
      "subject": "Compiler Design",
      "chapter": "Runtime Environments",
      "subtopic": null
    },
    {
      "fileName": "GATE_CS_1996.csv",
      "questionNumber": "15",
      "subject": "Algorithms",
      "chapter": "Basic Techniques",
      "subtopic": "Searching, sorting, hashing"
    },
    {
      "fileName": "GATE_CS_1996.csv",
      "questionNumber": "16",
      "subject": "Algorithms",
      "chapter": "Complexity Analysis",
      "subtopic": "Asymptotic worst case time and space complexity"
    },
    {
      "fileName": "GATE_CS_1996.csv",
      "questionNumber": "17",
      "subject": "Databases",
      "chapter": "Data Models",
      "subtopic": "ER-model, Relational model: relational algebra, tuple calculus, SQL"
    },
    {
      "fileName": "GATE_CS_1996.csv",
      "questionNumber": "18",
      "subject": "Engineering Mathematics",
      "chapter": "Probability and Statistics",
      "subtopic": "Conditional probability and Bayes theorem"
    },
    {
      "fileName": "GATE_CS_1996.csv",
      "questionNumber": "19",
      "subject": "Engineering Mathematics",
      "chapter": "Probability and Statistics",
      "subtopic": null
    },
    {
      "fileName": "GATE_CS_1996.csv",
      "questionNumber": "20",
      "subject": "Engineering Mathematics",
      "chapter": "Discrete Mathematics",
      "subtopic": "Sets, Relations, and Functions"
    },
    {
      "fileName": "GATE_CS_1996.csv",
      "questionNumber": "21",
      "subject": "Engineering Mathematics",
      "chapter": "Discrete Mathematics",
      "subtopic": "Counting, recurrence relations, generating functions"
    },
    {
      "fileName": "GATE_CS_1996.csv",
      "questionNumber": "22",
      "subject": null,
      "chapter": null,
      "subtopic": null
    },
    {
      "fileName": "GATE_CS_1996.csv",
      "questionNumber": "23",
      "subject": "Engineering Mathematics",
      "chapter": "Discrete Mathematics",
      "subtopic": "Sets, Relations, and Functions"
    },
    {
      "fileName": "GATE_CS_1996.csv",
      "questionNumber": "24",
      "subject": "Engineering Mathematics",
      "chapter": "Discrete Mathematics",
      "subtopic": "Sets, Relations, and Functions"
    },
    {
      "fileName": "GATE_CS_1996.csv",
      "questionNumber": "25",
      "subject": "Engineering Mathematics",
      "chapter": "Discrete Mathematics",
      "subtopic": "Sets, Relations, and Functions"
    },
    {
      "fileName": "GATE_CS_1996.csv",
      "questionNumber": "26",
      "subject": "Engineering Mathematics",
      "chapter": "Discrete Mathematics",
      "subtopic": "Sets, Relations, and Functions"
    },
    {
      "fileName": "GATE_CS_1996.csv",
      "questionNumber": "27",
      "subject": null,
      "chapter": null,
      "subtopic": null
    },
    {
      "fileName": "GATE_CS_1996.csv",
      "questionNumber": "28",
      "subject": "Engineering Mathematics",
      "chapter": "Discrete Mathematics",
      "subtopic": "Sets, Relations, and Functions"
    },
    {
      "fileName": "GATE_CS_1996.csv",
      "questionNumber": "29",
      "subject": "Engineering Mathematics",
      "chapter": "Linear Algebra",
      "subtopic": "Matrices and Determinants"
    },
    {
      "fileName": "GATE_CS_1996.csv",
      "questionNumber": "30",
      "subject": "Engineering Mathematics",
      "chapter": "Linear Algebra",
      "subtopic": "System of Linear Equations"
    },
    {
      "fileName": "GATE_CS_1996.csv",
      "questionNumber": "31",
      "subject": "Engineering Mathematics",
      "chapter": "Linear Algebra",
      "subtopic": "Matrices and Determinants"
    },
    {
      "fileName": "GATE_CS_1996.csv",
      "questionNumber": "32",
      "subject": "Digital Logic",
      "chapter": "Boolean Algebra",
      "subtopic": "Minimization"
    },
    {
      "fileName": "GATE_CS_1996.csv",
      "questionNumber": "33",
      "subject": "Digital Logic",
      "chapter": "Boolean Algebra",
      "subtopic": "Circuits: Combinational and sequential circuits."
    },
    {
      "fileName": "GATE_CS_1996.csv",
      "questionNumber": "34",
      "subject": "Digital Logic",
      "chapter": "Boolean Algebra",
      "subtopic": "Circuits: Combinational and sequential circuits."
    },
    {
      "fileName": "GATE_CS_1996.csv",
      "questionNumber": "35",
      "subject": "Digital Logic",
      "chapter": "Number Representations",
      "subtopic": "Number representations and computer arithmetic (fixed and floating point)."
    },
    {
      "fileName": "GATE_CS_1996.csv",
      "questionNumber": "36",
      "subject": "Digital Logic",
      "chapter": "Boolean Algebra",
      "subtopic": "Minimization"
    },
    {
      "fileName": "GATE_CS_1996.csv",
      "questionNumber": "37",
      "subject": "Digital Logic",
      "chapter": "Boolean Algebra",
      "subtopic": "Circuits: Combinational and sequential circuits."
    },
    {
      "fileName": "GATE_CS_1996.csv",
      "questionNumber": "38",
      "subject": "Digital Logic",
      "chapter": "Number Representations",
      "subtopic": "Number representations and computer arithmetic (fixed and floating point)."
    },
    {
      "fileName": "GATE_CS_1996.csv",
      "questionNumber": "39",
      "subject": "Digital Logic",
      "chapter": "Boolean Algebra",
      "subtopic": "Circuits: Combinational and sequential circuits."
    },
    {
      "fileName": "GATE_CS_1996.csv",
      "questionNumber": "40",
      "subject": "Theory of Computation",
      "chapter": "Formal Languages and Automata",
      "subtopic": "Regular expressions and finite automata"
    },
    {
      "fileName": "GATE_CS_1996.csv",
      "questionNumber": "41",
      "subject": "Theory of Computation",
      "chapter": "Language Properties",
      "subtopic": "Regular and context-free languages, pumping lemma"
    },
    {
      "fileName": "GATE_CS_1996.csv",
      "questionNumber": "42",
      "subject": "Theory of Computation",
      "chapter": "Formal Languages and Automata",
      "subtopic": "Regular expressions and finite automata"
    },
    {
      "fileName": "GATE_CS_1996.csv",
      "questionNumber": "43",
      "subject": "Theory of Computation",
      "chapter": "Formal Languages and Automata",
      "subtopic": "Regular expressions and finite automata"
    },
    {
      "fileName": "GATE_CS_1996.csv",
      "questionNumber": "44",
      "subject": "Theory of Computation",
      "chapter": "Formal Languages and Automata",
      "subtopic": "Context-free grammars and push-down automata"
    },
    {
      "fileName": "GATE_CS_1996.csv",
      "questionNumber": "45",
      "subject": "Theory of Computation",
      "chapter": "Formal Languages and Automata",
      "subtopic": "Context-free grammars and push-down automata"
    },
    {
      "fileName": "GATE_CS_1996.csv",
      "questionNumber": "46",
      "subject": "Theory of Computation",
      "chapter": "Formal Languages and Automata",
      "subtopic": "Context-free grammars and push-down automata"
    },
    {
      "fileName": "GATE_CS_1996.csv",
      "questionNumber": "47",
      "subject": "Theory of Computation",
      "chapter": "Language Properties",
      "subtopic": "Regular and context-free languages, pumping lemma"
    },
    {
      "fileName": "GATE_CS_1996.csv",
      "questionNumber": "48",
      "subject": null,
      "chapter": null,
      "subtopic": null
    },
    {
      "fileName": "GATE_CS_1996.csv",
      "questionNumber": "49",
      "subject": "Engineering Mathematics",
      "chapter": "Calculus",
      "subtopic": null
    },
    {
      "fileName": "GATE_CS_1996.csv",
      "questionNumber": "50",
      "subject": "Engineering Mathematics",
      "chapter": "Calculus",
      "subtopic": "Limits and Continuity"
    },
    {
      "fileName": "GATE_CS_1996.csv",
      "questionNumber": "51",
      "subject": "Engineering Mathematics",
      "chapter": "Calculus",
      "subtopic": null
    },
    {
      "fileName": "GATE_CS_1996.csv",
      "questionNumber": "52",
      "subject": "Computer Organization and Architecture",
      "chapter": "Instruction Set Architecture",
      "subtopic": "Machine instructions and addressing modes"
    },
    {
      "fileName": "GATE_CS_1996.csv",
      "questionNumber": "53",
      "subject": "Computer Organization and Architecture",
      "chapter": "Memory Hierarchy",
      "subtopic": "Cache, main memory and secondary storage"
    },
    {
      "fileName": "GATE_CS_1996.csv",
      "questionNumber": "54",
      "subject": "Computer Organization and Architecture",
      "chapter": "Input/Output (I/O)",
      "subtopic": "I/O interface (interrupt and DMA mode)"
    },
    {
      "fileName": "GATE_CS_1996.csv",
      "questionNumber": "55",
      "subject": "Computer Organization and Architecture",
      "chapter": "Input/Output (I/O)",
      "subtopic": "I/O interface (interrupt and DMA mode)"
    },
    {
      "fileName": "GATE_CS_1996.csv",
      "questionNumber": "56",
      "subject": "Computer Organization and Architecture",
      "chapter": "Instruction Set Architecture",
      "subtopic": "Machine instructions and addressing modes"
    },
    {
      "fileName": "GATE_CS_1996.csv",
      "questionNumber": "57",
      "subject": "Computer Organization and Architecture",
      "chapter": "Central Processing Unit (CPU)",
      "subtopic": "ALU, data-path and control unit"
    },
    {
      "fileName": "GATE_CS_1996.csv",
      "questionNumber": "58",
      "subject": "Computer Organization and Architecture",
      "chapter": "Instruction Set Architecture",
      "subtopic": "Machine instructions and addressing modes"
    },
    {
      "fileName": "GATE_CS_1996.csv",
      "questionNumber": "59",
      "subject": "Engineering Mathematics",
      "chapter": "Discrete Mathematics",
      "subtopic": "Logic: Propositional and first order logic."
    },
    {
      "fileName": "GATE_CS_1996.csv",
      "questionNumber": "60",
      "subject": "Operating System",
      "chapter": "Scheduling",
      "subtopic": "CPU and I/O scheduling"
    },
    {
      "fileName": "GATE_CS_1996.csv",
      "questionNumber": "61",
      "subject": "Operating System",
      "chapter": "Concurrency",
      "subtopic": "Inter-process communication, concurrency and synchronization, Deadlock"
    },
    {
      "fileName": "GATE_CS_1996.csv",
      "questionNumber": "62",
      "subject": "Operating System",
      "chapter": "Concurrency",
      "subtopic": "Inter-process communication, concurrency and synchronization, Deadlock"
    },
    {
      "fileName": "GATE_CS_1996.csv",
      "questionNumber": "63",
      "subject": "Operating System",
      "chapter": "Concurrency",
      "subtopic": "Inter-process communication, concurrency and synchronization, Deadlock"
    },
    {
      "fileName": "GATE_CS_1996.csv",
      "questionNumber": "64",
      "subject": "Programming and Data Structures",
      "chapter": "Linear Data Structures",
      "subtopic": "Arrays, stacks, queues, linked lists"
    },
    {
      "fileName": "GATE_CS_1996.csv",
      "questionNumber": "65",
      "subject": "Programming and Data Structures",
      "chapter": "Non-Linear Data Structures",
      "subtopic": "Trees, binary search trees, binary heaps, graphs"
    },
    {
      "fileName": "GATE_CS_1996.csv",
      "questionNumber": "66",
      "subject": "Programming and Data Structures",
      "chapter": "Non-Linear Data Structures",
      "subtopic": "Trees, binary search trees, binary heaps, graphs"
    },
    {
      "fileName": "GATE_CS_1996.csv",
      "questionNumber": "67",
      "subject": "Programming and Data Structures",
      "chapter": "Non-Linear Data Structures",
      "subtopic": "Trees, binary search trees, binary heaps, graphs"
    },
    {
      "fileName": "GATE_CS_1996.csv",
      "questionNumber": "68",
      "subject": "Algorithms",
      "chapter": "Basic Techniques",
      "subtopic": "Searching, sorting, hashing"
    },
    {
      "fileName": "GATE_CS_1996.csv",
      "questionNumber": "69",
      "subject": "Algorithms",
      "chapter": "Basic Techniques",
      "subtopic": "Searching, sorting, hashing"
    },
    {
      "fileName": "GATE_CS_1996.csv",
      "questionNumber": "70",
      "subject": "Programming and Data Structures",
      "chapter": "Non-Linear Data Structures",
      "subtopic": "Trees, binary search trees, binary heaps, graphs"
    },
    {
      "fileName": "GATE_CS_1996.csv",
      "questionNumber": "71",
      "subject": "Compiler Design",
      "chapter": "Phases of Compilation",
      "subtopic": "Lexical analysis, parsing, syntax-directed translation"
    },
    {
      "fileName": "GATE_CS_1996.csv",
      "questionNumber": "72",
      "subject": "Programming and Data Structures",
      "chapter": "Non-Linear Data Structures",
      "subtopic": "Trees, binary search trees, binary heaps, graphs"
    },
    {
      "fileName": "GATE_CS_1996.csv",
      "questionNumber": "73",
      "subject": "Compiler Design",
      "chapter": "Phases of Compilation",
      "subtopic": "Lexical analysis, parsing, syntax-directed translation"
    },
    {
      "fileName": "GATE_CS_1996.csv",
      "questionNumber": "74",
      "subject": "Compiler Design",
      "chapter": "Phases of Compilation",
      "subtopic": "Lexical analysis, parsing, syntax-directed translation"
    },
    {
      "fileName": "GATE_CS_1996.csv",
      "questionNumber": "75",
      "subject": "Compiler Design",
      "chapter": null,
      "subtopic": null
    },
    {
      "fileName": "GATE_CS_1997.csv",
      "questionNumber": "1",
      "subject": "Operating System",
      "chapter": "Concurrency",
      "subtopic": "Inter-process communication, concurrency and synchronization, Deadlock"
    },
    {
      "fileName": "GATE_CS_1997.csv",
      "questionNumber": "2",
      "subject": "Programming and Data Structures",
      "chapter": "Linear Data Structures",
      "subtopic": "Arrays, stacks, queues, linked lists"
    },
    {
      "fileName": "GATE_CS_1997.csv",
      "questionNumber": "3",
      "subject": "Algorithms",
      "chapter": "Graph Algorithms",
      "subtopic": "Graph traversals, minimum spanning trees, shortest paths"
    },
    {
      "fileName": "GATE_CS_1997.csv",
      "questionNumber": "4",
      "subject": "Algorithms",
      "chapter": "Algorithm Design Techniques",
      "subtopic": "Greedy, dynamic programming and divide-and-conquer"
    },
    {
      "fileName": "GATE_CS_1997.csv",
      "questionNumber": "5",
      "subject": "Programming and Data Structures",
      "chapter": "Linear Data Structures",
      "subtopic": "Arrays, stacks, queues, linked lists"
    },
    {
      "fileName": "GATE_CS_1997.csv",
      "questionNumber": "6",
      "subject": "Operating System",
      "chapter": "Memory Management",
      "subtopic": "Memory management and virtual memory"
    },
    {
      "fileName": "GATE_CS_1997.csv",
      "questionNumber": "7",
      "subject": "Operating System",
      "chapter": "Memory Management",
      "subtopic": "Memory management and virtual memory"
    },
    {
      "fileName": "GATE_CS_1997.csv",
      "questionNumber": "8",
      "subject": "Operating System",
      "chapter": "Memory Management",
      "subtopic": "Memory management and virtual memory"
    },
    {
      "fileName": "GATE_CS_1997.csv",
      "questionNumber": "9",
      "subject": "Programming and Data Structures",
      "chapter": "Linear Data Structures",
      "subtopic": "Arrays, stacks, queues, linked lists"
    },
    {
      "fileName": "GATE_CS_1997.csv",
      "questionNumber": "10",
      "subject": "Compiler Design",
      "chapter": "Runtime Environments",
      "subtopic": null
    },
    {
      "fileName": "GATE_CS_1997.csv",
      "questionNumber": "11",
      "subject": "Compiler Design",
      "chapter": "Runtime Environments",
      "subtopic": null
    },
    {
      "fileName": "GATE_CS_1997.csv",
      "questionNumber": "12",
      "subject": "Operating System",
      "chapter": "File Systems",
      "subtopic": null
    },
    {
      "fileName": "GATE_CS_1997.csv",
      "questionNumber": "13",
      "subject": "Operating System",
      "chapter": "Input/Output (I/O)",
      "subtopic": "I/O interface (interrupt and DMA mode)"
    },
    {
      "fileName": "GATE_CS_1997.csv",
      "questionNumber": "14",
      "subject": "Compiler Design",
      "chapter": "Runtime Environments",
      "subtopic": null
    },
    {
      "fileName": "GATE_CS_1997.csv",
      "questionNumber": "15",
      "subject": "Compiler Design",
      "chapter": "Phases of Compilation",
      "subtopic": "Lexical analysis, parsing, syntax-directed translation"
    },
    {
      "fileName": "GATE_CS_1997.csv",
      "questionNumber": "16",
      "subject": "Engineering Mathematics",
      "chapter": "Discrete Mathematics",
      "subtopic": "Counting, recurrence relations, generating functions"
    },
    {
      "fileName": "GATE_CS_1997.csv",
      "questionNumber": "17",
      "subject": "Algorithms",
      "chapter": "Complexity Analysis",
      "subtopic": "Asymptotic worst case time and space complexity"
    },
    {
      "fileName": "GATE_CS_1997.csv",
      "questionNumber": "18",
      "subject": "Databases",
      "chapter": "Database Design",
      "subtopic": "Integrity constraints, normal forms"
    },
    {
      "fileName": "GATE_CS_1997.csv",
      "questionNumber": "19",
      "subject": "Databases",
      "chapter": "Data Models",
      "subtopic": "ER-model, Relational model: relational algebra, tuple calculus, SQL"
    },
    {
      "fileName": "GATE_CS_1997.csv",
      "questionNumber": "20",
      "subject": "Databases",
      "chapter": "Database Design",
      "subtopic": "Integrity constraints, normal forms"
    },
    {
      "fileName": "GATE_CS_1997.csv",
      "questionNumber": "21",
      "subject": "Databases",
      "chapter": "File Organization and Indexing",
      "subtopic": "File organization, indexing (e.g., B and B+ trees)"
    },
    {
      "fileName": "GATE_CS_1997.csv",
      "questionNumber": "22",
      "subject": "Engineering Mathematics",
      "chapter": "Probability and Statistics",
      "subtopic": "Conditional probability and Bayes theorem"
    },
    {
      "fileName": "GATE_CS_1997.csv",
      "questionNumber": "23",
      "subject": "Engineering Mathematics",
      "chapter": "Calculus",
      "subtopic": null
    },
    {
      "fileName": "GATE_CS_1997.csv",
      "questionNumber": "24",
      "subject": "Engineering Mathematics",
      "chapter": "Discrete Mathematics",
      "subtopic": "Sets, Relations, and Functions"
    },
    {
      "fileName": "GATE_CS_1997.csv",
      "questionNumber": "25",
      "subject": "Engineering Mathematics",
      "chapter": "Discrete Mathematics",
      "subtopic": "Sets, Relations, and Functions"
    },
    {
      "fileName": "GATE_CS_1997.csv",
      "questionNumber": "26",
      "subject": "Engineering Mathematics",
      "chapter": "Discrete Mathematics",
      "subtopic": "Sets, Relations, and Functions"
    },
    {
      "fileName": "GATE_CS_1997.csv",
      "questionNumber": "27",
      "subject": "Engineering Mathematics",
      "chapter": "Discrete Mathematics",
      "subtopic": "Combinatorics: Counting, recurrence relations, generating functions."
    },
    {
      "fileName": "GATE_CS_1997.csv",
      "questionNumber": "28",
      "subject": "Engineering Mathematics",
      "chapter": "Discrete Mathematics",
      "subtopic": "Algebraic Structures: Monoids, Groups."
    },
    {
      "fileName": "GATE_CS_1997.csv",
      "questionNumber": "29",
      "subject": "Engineering Mathematics",
      "chapter": "Discrete Mathematics",
      "subtopic": "Sets, Relations, and Functions"
    },
    {
      "fileName": "GATE_CS_1997.csv",
      "questionNumber": "30",
      "subject": "Engineering Mathematics",
      "chapter": "Linear Algebra",
      "subtopic": "Matrices and Determinants"
    },
    {
      "fileName": "GATE_CS_1997.csv",
      "questionNumber": "31",
      "subject": "Engineering Mathematics",
      "chapter": "Linear Algebra",
      "subtopic": "Matrices and Determinants"
    },
    {
      "fileName": "GATE_CS_1997.csv",
      "questionNumber": "32",
      "subject": "Digital Logic",
      "chapter": "Boolean Algebra",
      "subtopic": "Minimization"
    },
    {
      "fileName": "GATE_CS_1997.csv",
      "questionNumber": "33",
      "subject": "Digital Logic",
      "chapter": "Number Representations",
      "subtopic": "Number representations and computer arithmetic (fixed and floating point)."
    },
    {
      "fileName": "GATE_CS_1997.csv",
      "questionNumber": "34",
      "subject": "Computer Organization and Architecture",
      "chapter": "Input/Output (I/O)",
      "subtopic": "I/O interface (interrupt and DMA mode)"
    },
    {
      "fileName": "GATE_CS_1997.csv",
      "questionNumber": "35",
      "subject": "Digital Logic",
      "chapter": "Boolean Algebra",
      "subtopic": "Minimization"
    },
    {
      "fileName": "GATE_CS_1997.csv",
      "questionNumber": "36",
      "subject": "Digital Logic",
      "chapter": "Number Representations",
      "subtopic": "Number representations and computer arithmetic (fixed and floating point)."
    },
    {
      "fileName": "GATE_CS_1997.csv",
      "questionNumber": "37",
      "subject": "Digital Logic",
      "chapter": "Boolean Algebra",
      "subtopic": "Minimization"
    },
    {
      "fileName": "GATE_CS_1997.csv",
      "questionNumber": "38",
      "subject": "Digital Logic",
      "chapter": "Boolean Algebra",
      "subtopic": null
    },
    {
      "fileName": "GATE_CS_1997.csv",
      "questionNumber": "39",
      "subject": "Digital Logic",
      "chapter": "Number Representations",
      "subtopic": "Number representations and computer arithmetic (fixed and floating point)."
    },
    {
      "fileName": "GATE_CS_1997.csv",
      "questionNumber": "40",
      "subject": "Theory of Computation",
      "chapter": "Formal Languages and Automata",
      "subtopic": "Regular expressions and finite automata"
    },
    {
      "fileName": "GATE_CS_1997.csv",
      "questionNumber": "41",
      "subject": "Theory of Computation",
      "chapter": "Language Properties",
      "subtopic": "Regular and context-free languages, pumping lemma"
    },
    {
      "fileName": "GATE_CS_1997.csv",
      "questionNumber": "42",
      "subject": "Theory of Computation",
      "chapter": "Formal Languages and Automata",
      "subtopic": "Regular expressions and finite automata"
    },
    {
      "fileName": "GATE_CS_1997.csv",
      "questionNumber": "43",
      "subject": "Theory of Computation",
      "chapter": "Formal Languages and Automata",
      "subtopic": "Regular expressions and finite automata"
    },
    {
      "fileName": "GATE_CS_1997.csv",
      "questionNumber": "44",
      "subject": "Theory of Computation",
      "chapter": "Formal Languages and Automata",
      "subtopic": "Context-free grammars and push-down automata"
    },
    {
      "fileName": "GATE_CS_1997.csv",
      "questionNumber": "45",
      "subject": "Theory of Computation",
      "chapter": "Computability",
      "subtopic": "Turing machines and undecidability"
    },
    {
      "fileName": "GATE_CS_1997.csv",
      "questionNumber": "46",
      "subject": "Theory of Computation",
      "chapter": "Computability",
      "subtopic": "Turing machines and undecidability"
    },
    {
      "fileName": "GATE_CS_1997.csv",
      "questionNumber": "47",
      "subject": "Engineering Mathematics",
      "chapter": "Calculus",
      "subtopic": "Integration"
    },
    {
      "fileName": "GATE_CS_1997.csv",
      "questionNumber": "48",
      "subject": "Engineering Mathematics",
      "chapter": "Calculus",
      "subtopic": null
    },
    {
      "fileName": "GATE_CS_1997.csv",
      "questionNumber": "49",
      "subject": "Engineering Mathematics",
      "chapter": "Calculus",
      "subtopic": null
    },
    {
      "fileName": "GATE_CS_1997.csv",
      "questionNumber": "50",
      "subject": "Engineering Mathematics",
      "chapter": "Calculus",
      "subtopic": "Extrema: Maxima and minima."
    },
    {
      "fileName": "GATE_CS_1997.csv",
      "questionNumber": "51",
      "subject": "Digital Logic",
      "chapter": "Number Representations",
      "subtopic": "Number representations and computer arithmetic (fixed and floating point)."
    },
    {
      "fileName": "GATE_CS_1997.csv",
      "questionNumber": "52",
      "subject": "Computer Organization and Architecture",
      "chapter": "Input/Output (I/O)",
      "subtopic": "I/O interface (interrupt and DMA mode)"
    },
    {
      "fileName": "GATE_CS_1997.csv",
      "questionNumber": "53",
      "subject": "Computer Organization and Architecture",
      "chapter": null,
      "subtopic": null
    },
    {
      "fileName": "GATE_CS_1997.csv",
      "questionNumber": "54",
      "subject": "Computer Organization and Architecture",
      "chapter": "Central Processing Unit (CPU)",
      "subtopic": "ALU, data-path and control unit"
    },
    {
      "fileName": "GATE_CS_1997.csv",
      "questionNumber": "55",
      "subject": "Computer Networks",
      "chapter": "Data Link Layer",
      "subtopic": "Framing, error detection, Medium Access Control, Ethernet bridging"
    },
    {
      "fileName": "GATE_CS_1997.csv",
      "questionNumber": "56",
      "subject": "Engineering Mathematics",
      "chapter": "Discrete Mathematics",
      "subtopic": "Logic: Propositional and first order logic."
    },
    {
      "fileName": "GATE_CS_1997.csv",
      "questionNumber": "57",
      "subject": "Operating System",
      "chapter": "Scheduling",
      "subtopic": "CPU and I/O scheduling"
    },
    {
      "fileName": "GATE_CS_1997.csv",
      "questionNumber": "58",
      "subject": "Operating System",
      "chapter": "Core Concepts",
      "subtopic": "System calls, processes, threads"
    },
    {
      "fileName": "GATE_CS_1997.csv",
      "questionNumber": "59",
      "subject": "Operating System",
      "chapter": "Concurrency",
      "subtopic": "Inter-process communication, concurrency and synchronization, Deadlock"
    },
    {
      "fileName": "GATE_CS_1997.csv",
      "questionNumber": "60",
      "subject": "Operating System",
      "chapter": "Concurrency",
      "subtopic": "Inter-process communication, concurrency and synchronization, Deadlock"
    },
    {
      "fileName": "GATE_CS_1997.csv",
      "questionNumber": "61",
      "subject": "Operating System",
      "chapter": "Concurrency",
      "subtopic": "Inter-process communication, concurrency and synchronization, Deadlock"
    },
    {
      "fileName": "GATE_CS_1997.csv",
      "questionNumber": "62",
      "subject": "Compiler Design",
      "chapter": "Runtime Environments",
      "subtopic": null
    },
    {
      "fileName": "GATE_CS_1997.csv",
      "questionNumber": "63",
      "subject": "Programming and Data Structures",
      "chapter": "Linear Data Structures",
      "subtopic": "Arrays, stacks, queues, linked lists"
    },
    {
      "fileName": "GATE_CS_1997.csv",
      "questionNumber": "64",
      "subject": "Programming and Data Structures",
      "chapter": "Linear Data Structures",
      "subtopic": "Arrays, stacks, queues, linked lists"
    },
    {
      "fileName": "GATE_CS_1997.csv",
      "questionNumber": "65",
      "subject": "Programming and Data Structures",
      "chapter": "Non-Linear Data Structures",
      "subtopic": "Trees, binary search trees, binary heaps, graphs"
    },
    {
      "fileName": "GATE_CS_1997.csv",
      "questionNumber": "66",
      "subject": "Programming and Data Structures",
      "chapter": "Non-Linear Data Structures",
      "subtopic": "Trees, binary search trees, binary heaps, graphs"
    },
    {
      "fileName": "GATE_CS_1997.csv",
      "questionNumber": "67",
      "subject": "Algorithms",
      "chapter": "Basic Techniques",
      "subtopic": "Searching, sorting, hashing"
    },
    {
      "fileName": "GATE_CS_1997.csv",
      "questionNumber": "68",
      "subject": "Engineering Mathematics",
      "chapter": "Discrete Mathematics",
      "subtopic": "Graph Theory: Connectivity, matching, colouring."
    },
    {
      "fileName": "GATE_CS_1997.csv",
      "questionNumber": "69",
      "subject": "Programming and Data Structures",
      "chapter": "Linear Data Structures",
      "subtopic": "Arrays, stacks, queues, linked lists"
    },
    {
      "fileName": "GATE_CS_1997.csv",
      "questionNumber": "70",
      "subject": "Compiler Design",
      "chapter": "Phases of Compilation",
      "subtopic": "Lexical analysis, parsing, syntax-directed translation"
    },
    {
      "fileName": "GATE_CS_1997.csv",
      "questionNumber": "71",
      "subject": "Compiler Design",
      "chapter": "Phases of Compilation",
      "subtopic": "Lexical analysis, parsing, syntax-directed translation"
    },
    {
      "fileName": "GATE_CS_1997.csv",
      "questionNumber": "72",
      "subject": "Compiler Design",
      "chapter": "Runtime Environments",
      "subtopic": null
    },
    {
      "fileName": "GATE_CS_1997.csv",
      "questionNumber": "73",
      "subject": "Computer Organization and Architecture",
      "chapter": "Central Processing Unit (CPU)",
      "subtopic": "ALU, data-path and control unit"
    },
    {
      "fileName": "GATE_CS_1997.csv",
      "questionNumber": "74",
      "subject": "Compiler Design",
      "chapter": null,
      "subtopic": null
    },
    {
      "fileName": "GATE_CS_1997.csv",
      "questionNumber": "75",
      "subject": "Theory of Computation",
      "chapter": "Formal Languages and Automata",
      "subtopic": "Context-free grammars and push-down automata"
    },
    {
      "fileName": "GATE_CS_1998.csv",
      "questionNumber": "1",
      "subject": "Operating System",
      "chapter": "Memory Management",
      "subtopic": "Memory management and virtual memory"
    },
    {
      "fileName": "GATE_CS_1998.csv",
      "questionNumber": "2",
      "subject": "Algorithms",
      "chapter": "Complexity Analysis",
      "subtopic": "Asymptotic worst case time and space complexity"
    },
    {
      "fileName": "GATE_CS_1998.csv",
      "questionNumber": "3",
      "subject": "Algorithms",
      "chapter": "Algorithm Design Techniques",
      "subtopic": "Greedy, dynamic programming and divide-and-conquer"
    },
    {
      "fileName": "GATE_CS_1998.csv",
      "questionNumber": "4",
      "subject": "Engineering Mathematics",
      "chapter": "Discrete Mathematics",
      "subtopic": "Counting, recurrence relations, generating functions"
    },
    {
      "fileName": "GATE_CS_1998.csv",
      "questionNumber": "5",
      "subject": "Programming and Data Structures",
      "chapter": "Recursion",
      "subtopic": null
    },
    {
      "fileName": "GATE_CS_1998.csv",
      "questionNumber": "6",
      "subject": "Programming and Data Structures",
      "chapter": "Linear Data Structures",
      "subtopic": "Arrays, stacks, queues, linked lists"
    },
    {
      "fileName": "GATE_CS_1998.csv",
      "questionNumber": "7",
      "subject": "Compiler Design",
      "chapter": "Runtime Environments",
      "subtopic": null
    },
    {
      "fileName": "GATE_CS_1998.csv",
      "questionNumber": "8",
      "subject": "Operating System",
      "chapter": "File Systems",
      "subtopic": null
    },
    {
      "fileName": "GATE_CS_1998.csv",
      "questionNumber": "9",
      "subject": "Operating System",
      "chapter": "Memory Management",
      "subtopic": "Memory management and virtual memory"
    },
    {
      "fileName": "GATE_CS_1998.csv",
      "questionNumber": "10",
      "subject": "Operating System",
      "chapter": "Concurrency",
      "subtopic": "Inter-process communication, concurrency and synchronization, Deadlock"
    },
    {
      "fileName": "GATE_CS_1998.csv",
      "questionNumber": "11",
      "subject": "Operating System",
      "chapter": "File Systems",
      "subtopic": null
    },
    {
      "fileName": "GATE_CS_1998.csv",
      "questionNumber": "12",
      "subject": "Computer Organization and Architecture",
      "chapter": "Input/Output (I/O)",
      "subtopic": "I/O interface (interrupt and DMA mode)"
    },
    {
      "fileName": "GATE_CS_1998.csv",
      "questionNumber": "13",
      "subject": "Computer Organization and Architecture",
      "chapter": "Input/Output (I/O)",
      "subtopic": "I/O interface (interrupt and DMA mode)"
    },
    {
      "fileName": "GATE_CS_1998.csv",
      "questionNumber": "14",
      "subject": "Operating System",
      "chapter": "File Systems",
      "subtopic": null
    },
    {
      "fileName": "GATE_CS_1998.csv",
      "questionNumber": "15",
      "subject": "Computer Organization and Architecture",
      "chapter": "Memory Hierarchy",
      "subtopic": "Cache, main memory and secondary storage"
    },
    {
      "fileName": "GATE_CS_1998.csv",
      "questionNumber": "16",
      "subject": "Compiler Design",
      "chapter": "Runtime Environments",
      "subtopic": null
    },
    {
      "fileName": "GATE_CS_1998.csv",
      "questionNumber": "17",
      "subject": "Databases",
      "chapter": "Data Models",
      "subtopic": "ER-model, Relational model: relational algebra, tuple calculus, SQL"
    },
    {
      "fileName": "GATE_CS_1998.csv",
      "questionNumber": "18",
      "subject": "Databases",
      "chapter": "Data Models",
      "subtopic": "ER-model, Relational model: relational algebra, tuple calculus, SQL"
    },
    {
      "fileName": "GATE_CS_1998.csv",
      "questionNumber": "19",
      "subject": "Databases",
      "chapter": "Database Design",
      "subtopic": "Integrity constraints, normal forms"
    },
    {
      "fileName": "GATE_CS_1998.csv",
      "questionNumber": "20",
      "subject": "Databases",
      "chapter": "Database Design",
      "subtopic": "Integrity constraints, normal forms"
    },
    {
      "fileName": "GATE_CS_1998.csv",
      "questionNumber": "21",
      "subject": "Databases",
      "chapter": "Data Models",
      "subtopic": "ER-model, Relational model: relational algebra, tuple calculus, SQL"
    },
    {
      "fileName": "GATE_CS_1998.csv",
      "questionNumber": "22",
      "subject": "Databases",
      "chapter": "Data Models",
      "subtopic": "ER-model, Relational model: relational algebra, tuple calculus, SQL"
    },
    {
      "fileName": "GATE_CS_1998.csv",
      "questionNumber": "23",
      "subject": "Databases",
      "chapter": "File Organization and Indexing",
      "subtopic": "File organization, indexing (e.g., B and B+ trees)"
    },
    {
      "fileName": "GATE_CS_1998.csv",
      "questionNumber": "24",
      "subject": "Engineering Mathematics",
      "chapter": "Probability and Statistics",
      "subtopic": null
    },
    {
      "fileName": "GATE_CS_1998.csv",
      "questionNumber": "25",
      "subject": "Engineering Mathematics",
      "chapter": "Probability and Statistics",
      "subtopic": null
    },
    {
      "fileName": "GATE_CS_1998.csv",
      "questionNumber": "26",
      "subject": "Engineering Mathematics",
      "chapter": "Discrete Mathematics",
      "subtopic": "Sets, Relations, and Functions"
    },
    {
      "fileName": "GATE_CS_1998.csv",
      "questionNumber": "27",
      "subject": "Engineering Mathematics",
      "chapter": "Discrete Mathematics",
      "subtopic": "Sets, Relations, and Functions"
    },
    {
      "fileName": "GATE_CS_1998.csv",
      "questionNumber": "28",
      "subject": "Engineering Mathematics",
      "chapter": "Discrete Mathematics",
      "subtopic": "Algebraic Structures: Monoids, Groups."
    },
    {
      "fileName": "GATE_CS_1998.csv",
      "questionNumber": "29",
      "subject": "Engineering Mathematics",
      "chapter": "Discrete Mathematics",
      "subtopic": "Sets, Relations, and Functions"
    },
    {
      "fileName": "GATE_CS_1998.csv",
      "questionNumber": "30",
      "subject": "Engineering Mathematics",
      "chapter": "Discrete Mathematics",
      "subtopic": "Combinatorics: Counting, recurrence relations, generating functions."
    },
    {
      "fileName": "GATE_CS_1998.csv",
      "questionNumber": "31",
      "subject": "Engineering Mathematics",
      "chapter": "Discrete Mathematics",
      "subtopic": "Sets, Relations, and Functions"
    },
    {
      "fileName": "GATE_CS_1998.csv",
      "questionNumber": "32",
      "subject": "Engineering Mathematics",
      "chapter": "Discrete Mathematics",
      "subtopic": "Sets, Relations, and Functions"
    },
    {
      "fileName": "GATE_CS_1998.csv",
      "questionNumber": "33",
      "subject": "Engineering Mathematics",
      "chapter": "Discrete Mathematics",
      "subtopic": "Combinatorics: Counting, recurrence relations, generating functions."
    },
    {
      "fileName": "GATE_CS_1998.csv",
      "questionNumber": "34",
      "subject": "Engineering Mathematics",
      "chapter": "Linear Algebra",
      "subtopic": "System of Linear Equations"
    },
    {
      "fileName": "GATE_CS_1998.csv",
      "questionNumber": "35",
      "subject": "Engineering Mathematics",
      "chapter": "Linear Algebra",
      "subtopic": "System of Linear Equations"
    },
    {
      "fileName": "GATE_CS_1998.csv",
      "questionNumber": "36",
      "subject": "Engineering Mathematics",
      "chapter": "Linear Algebra",
      "subtopic": "Matrices and Determinants"
    },
    {
      "fileName": "GATE_CS_1998.csv",
      "questionNumber": "37",
      "subject": "Digital Logic",
      "chapter": "Boolean Algebra",
      "subtopic": "Minimization"
    },
    {
      "fileName": "GATE_CS_1998.csv",
      "questionNumber": "38",
      "subject": "Digital Logic",
      "chapter": "Boolean Algebra",
      "subtopic": null
    },
    {
      "fileName": "GATE_CS_1998.csv",
      "questionNumber": "39",
      "subject": "Digital Logic",
      "chapter": "Boolean Algebra",
      "subtopic": "Circuits: Combinational and sequential circuits."
    },
    {
      "fileName": "GATE_CS_1998.csv",
      "questionNumber": "40",
      "subject": "Digital Logic",
      "chapter": "Boolean Algebra",
      "subtopic": null
    },
    {
      "fileName": "GATE_CS_1998.csv",
      "questionNumber": "41",
      "subject": "Digital Logic",
      "chapter": "Number Representations",
      "subtopic": "Number representations and computer arithmetic (fixed and floating point)."
    },
    {
      "fileName": "GATE_CS_1998.csv",
      "questionNumber": "42",
      "subject": "Digital Logic",
      "chapter": null,
      "subtopic": null
    },
    {
      "fileName": "GATE_CS_1998.csv",
      "questionNumber": "43",
      "subject": "Digital Logic",
      "chapter": "Boolean Algebra",
      "subtopic": "Circuits: Combinational and sequential circuits."
    },
    {
      "fileName": "GATE_CS_1998.csv",
      "questionNumber": "44",
      "subject": "Digital Logic",
      "chapter": "Boolean Algebra",
      "subtopic": null
    },
    {
      "fileName": "GATE_CS_1998.csv",
      "questionNumber": "45",
      "subject": "Digital Logic",
      "chapter": "Number Representations",
      "subtopic": null
    },
    {
      "fileName": "GATE_CS_1998.csv",
      "questionNumber": "46",
      "subject": "Theory of Computation",
      "chapter": "Formal Languages and Automata",
      "subtopic": "Regular expressions and finite automata"
    },
    {
      "fileName": "GATE_CS_1998.csv",
      "questionNumber": "47",
      "subject": "Theory of Computation",
      "chapter": "Formal Languages and Automata",
      "subtopic": "Regular expressions and finite automata"
    },
    {
      "fileName": "GATE_CS_1998.csv",
      "questionNumber": "48",
      "subject": "Theory of Computation",
      "chapter": "Formal Languages and Automata",
      "subtopic": "Regular expressions and finite automata"
    },
    {
      "fileName": "GATE_CS_1998.csv",
      "questionNumber": "49",
      "subject": "Theory of Computation",
      "chapter": "Formal Languages and Automata",
      "subtopic": "Regular expressions and finite automata"
    },
    {
      "fileName": "GATE_CS_1998.csv",
      "questionNumber": "50",
      "subject": "Theory of Computation",
      "chapter": "Formal Languages and Automata",
      "subtopic": "Regular expressions and finite automata"
    },
    {
      "fileName": "GATE_CS_1998.csv",
      "questionNumber": "51",
      "subject": "Theory of Computation",
      "chapter": "Formal Languages and Automata",
      "subtopic": "Regular expressions and finite automata"
    },
    {
      "fileName": "GATE_CS_1998.csv",
      "questionNumber": "52",
      "subject": null,
      "chapter": null,
      "subtopic": null
    },
    {
      "fileName": "GATE_CS_1998.csv",
      "questionNumber": "53",
      "subject": "Theory of Computation",
      "chapter": null,
      "subtopic": null
    },
    {
      "fileName": "GATE_CS_1998.csv",
      "questionNumber": "54",
      "subject": "Theory of Computation",
      "chapter": "Formal Languages and Automata",
      "subtopic": "Context-free grammars and push-down automata"
    },
    {
      "fileName": "GATE_CS_1998.csv",
      "questionNumber": "55",
      "subject": "Engineering Mathematics",
      "chapter": "Calculus",
      "subtopic": "Limits and Continuity"
    },
    {
      "fileName": "GATE_CS_1998.csv",
      "questionNumber": "56",
      "subject": "Engineering Mathematics",
      "chapter": "Calculus",
      "subtopic": null
    },
    {
      "fileName": "GATE_CS_1998.csv",
      "questionNumber": "57",
      "subject": "Engineering Mathematics",
      "chapter": "Calculus",
      "subtopic": "Extrema: Maxima and minima."
    },
    {
      "fileName": "GATE_CS_1998.csv",
      "questionNumber": "58",
      "subject": "Engineering Mathematics",
      "chapter": "Discrete Mathematics",
      "subtopic": "Combinatorics: Counting, recurrence relations, generating functions."
    },
    {
      "fileName": "GATE_CS_1998.csv",
      "questionNumber": "59",
      "subject": "Computer Organization and Architecture",
      "chapter": "Memory Hierarchy",
      "subtopic": "Cache, main memory and secondary storage"
    },
    {
      "fileName": "GATE_CS_1998.csv",
      "questionNumber": "60",
      "subject": "Computer Organization and Architecture",
      "chapter": "Input/Output (I/O)",
      "subtopic": "I/O interface (interrupt and DMA mode)"
    },
    {
      "fileName": "GATE_CS_1998.csv",
      "questionNumber": "61",
      "subject": "Computer Organization and Architecture",
      "chapter": "Instruction Set Architecture",
      "subtopic": null
    },
    {
      "fileName": "GATE_CS_1998.csv",
      "questionNumber": "62",
      "subject": "Operating System",
      "chapter": "Memory Management",
      "subtopic": "Memory management and virtual memory"
    },
    {
      "fileName": "GATE_CS_1998.csv",
      "questionNumber": "63",
      "subject": null,
      "chapter": null,
      "subtopic": null
    },
    {
      "fileName": "GATE_CS_1998.csv",
      "questionNumber": "64",
      "subject": "Computer Networks",
      "chapter": "Data Link Layer",
      "subtopic": "Framing, error detection, Medium Access Control, Ethernet bridging"
    },
    {
      "fileName": "GATE_CS_1998.csv",
      "questionNumber": "65",
      "subject": "Engineering Mathematics",
      "chapter": "Discrete Mathematics",
      "subtopic": "Logic: Propositional and first order logic."
    },
    {
      "fileName": "GATE_CS_1998.csv",
      "questionNumber": "66",
      "subject": "Operating System",
      "chapter": "Scheduling",
      "subtopic": "CPU and I/O scheduling"
    },
    {
      "fileName": "GATE_CS_1998.csv",
      "questionNumber": "67",
      "subject": "Operating System",
      "chapter": "Scheduling",
      "subtopic": "CPU and I/O scheduling"
    },
    {
      "fileName": "GATE_CS_1998.csv",
      "questionNumber": "68",
      "subject": "Operating System",
      "chapter": "Concurrency",
      "subtopic": "Inter-process communication, concurrency and synchronization, Deadlock"
    },
    {
      "fileName": "GATE_CS_1998.csv",
      "questionNumber": "69",
      "subject": "Operating System",
      "chapter": "Concurrency",
      "subtopic": "Inter-process communication, concurrency and synchronization, Deadlock"
    },
    {
      "fileName": "GATE_CS_1998.csv",
      "questionNumber": "70",
      "subject": "Programming and Data Structures",
      "chapter": "Linear Data Structures",
      "subtopic": "Arrays, stacks, queues, linked lists"
    },
    {
      "fileName": "GATE_CS_1998.csv",
      "questionNumber": "71",
      "subject": "Programming and Data Structures",
      "chapter": "Non-Linear Data Structures",
      "subtopic": "Trees, binary search trees, binary heaps, graphs"
    },
    {
      "fileName": "GATE_CS_1998.csv",
      "questionNumber": "72",
      "subject": "Programming and Data Structures",
      "chapter": "Linear Data Structures",
      "subtopic": "Arrays, stacks, queues, linked lists"
    },
    {
      "fileName": "GATE_CS_1998.csv",
      "questionNumber": "73",
      "subject": "Programming and Data Structures",
      "chapter": "Non-Linear Data Structures",
      "subtopic": "Trees, binary search trees, binary heaps, graphs"
    },
    {
      "fileName": "GATE_CS_1998.csv",
      "questionNumber": "74",
      "subject": "Compiler Design",
      "chapter": "Phases of Compilation",
      "subtopic": "Lexical analysis, parsing, syntax-directed translation"
    },
    {
      "fileName": "GATE_CS_1998.csv",
      "questionNumber": "75",
      "subject": null,
      "chapter": null,
      "subtopic": null
    },
    {
      "fileName": "GATE_CS_1998.csv",
      "questionNumber": "76",
      "subject": "Compiler Design",
      "chapter": "Phases of Compilation",
      "subtopic": "Lexical analysis, parsing, syntax-directed translation"
    },
    {
      "fileName": "GATE_CS_1998.csv",
      "questionNumber": "77",
      "subject": "Compiler Design",
      "chapter": "Phases of Compilation",
      "subtopic": "Lexical analysis, parsing, syntax-directed translation"
    },
    {
      "fileName": "GATE_CS_1998.csv",
      "questionNumber": "78",
      "subject": null,
      "chapter": null,
      "subtopic": null
    },
    {
      "fileName": "GATE_CS_1998.csv",
      "questionNumber": "79",
      "subject": "Theory of Computation",
      "chapter": "Formal Languages and Automata",
      "subtopic": "Context-free grammars and push-down automata"
    },
    {
      "fileName": "GATE_CS_1998.csv",
      "questionNumber": "80",
      "subject": "Programming and Data Structures",
      "chapter": "Non-Linear Data Structures",
      "subtopic": "Trees, binary search trees, binary heaps, graphs"
    },
    {
      "fileName": "GATE_CS_1998.csv",
      "questionNumber": "81",
      "subject": "Compiler Design",
      "chapter": "Phases of Compilation",
      "subtopic": "Lexical analysis, parsing, syntax-directed translation"
    },
    {
      "fileName": "GATE_CS_1998.csv",
      "questionNumber": "82",
      "subject": "Compiler Design",
      "chapter": "Runtime Environments",
      "subtopic": null
    },
    {
      "fileName": "GATE_CS_1998.csv",
      "questionNumber": "83",
      "subject": "Operating System",
      "chapter": null,
      "subtopic": null
    },
    {
      "fileName": "GATE_CS_1999.csv",
      "questionNumber": "1",
      "subject": "Theory of Computation",
      "chapter": "Computability",
      "subtopic": "Turing machines and undecidability"
    },
    {
      "fileName": "GATE_CS_1999.csv",
      "questionNumber": "2",
      "subject": "Operating System",
      "chapter": "Core Concepts",
      "subtopic": "System calls, processes, threads"
    },
    {
      "fileName": "GATE_CS_1999.csv",
      "questionNumber": "3",
      "subject": "Programming and Data Structures",
      "chapter": "Recursion",
      "subtopic": null
    },
    {
      "fileName": "GATE_CS_1999.csv",
      "questionNumber": "4",
      "subject": "Algorithms",
      "chapter": "Complexity Analysis",
      "subtopic": "Asymptotic worst case time and space complexity"
    },
    {
      "fileName": "GATE_CS_1999.csv",
      "questionNumber": "5",
      "subject": "Algorithms",
      "chapter": "Basic Techniques",
      "subtopic": "Searching, sorting, hashing"
    },
    {
      "fileName": "GATE_CS_1999.csv",
      "questionNumber": "6",
      "subject": "Algorithms",
      "chapter": "Basic Techniques",
      "subtopic": "Searching, sorting, hashing"
    },
    {
      "fileName": "GATE_CS_1999.csv",
      "questionNumber": "7",
      "subject": "Algorithms",
      "chapter": "Basic Techniques",
      "subtopic": "Searching, sorting, hashing"
    },
    {
      "fileName": "GATE_CS_1999.csv",
      "questionNumber": "8",
      "subject": "Algorithms",
      "chapter": "Basic Techniques",
      "subtopic": "Searching, sorting, hashing"
    },
    {
      "fileName": "GATE_CS_1999.csv",
      "questionNumber": "9",
      "subject": "Operating System",
      "chapter": null,
      "subtopic": null
    },
    {
      "fileName": "GATE_CS_1999.csv",
      "questionNumber": "10",
      "subject": "Operating System",
      "chapter": "Memory Management",
      "subtopic": "Memory management and virtual memory"
    },
    {
      "fileName": "GATE_CS_1999.csv",
      "questionNumber": "11",
      "subject": "Operating System",
      "chapter": "Memory Management",
      "subtopic": "Memory management and virtual memory"
    },
    {
      "fileName": "GATE_CS_1999.csv",
      "questionNumber": "12",
      "subject": "Compiler Design",
      "chapter": "Runtime Environments",
      "subtopic": null
    },
    {
      "fileName": "GATE_CS_1999.csv",
      "questionNumber": "13",
      "subject": "Operating System",
      "chapter": "Core Concepts",
      "subtopic": "System calls, processes, threads"
    },
    {
      "fileName": "GATE_CS_1999.csv",
      "questionNumber": "14",
      "subject": "Computer Organization and Architecture",
      "chapter": "Memory Hierarchy",
      "subtopic": "Cache, main memory and secondary storage"
    },
    {
      "fileName": "GATE_CS_1999.csv",
      "questionNumber": "15",
      "subject": "Compiler Design",
      "chapter": "Phases of Compilation",
      "subtopic": "Lexical analysis, parsing, syntax-directed translation"
    },
    {
      "fileName": "GATE_CS_1999.csv",
      "questionNumber": "16",
      "subject": "Databases",
      "chapter": "Data Models",
      "subtopic": "ER-model, Relational model: relational algebra, tuple calculus, SQL"
    },
    {
      "fileName": "GATE_CS_1999.csv",
      "questionNumber": "17",
      "subject": "Databases",
      "chapter": "Data Models",
      "subtopic": "ER-model, Relational model: relational algebra, tuple calculus, SQL"
    },
    {
      "fileName": "GATE_CS_1999.csv",
      "questionNumber": "18",
      "subject": "Databases",
      "chapter": "Database Design",
      "subtopic": "Integrity constraints, normal forms"
    },
    {
      "fileName": "GATE_CS_1999.csv",
      "questionNumber": "19",
      "subject": "Databases",
      "chapter": "Database Design",
      "subtopic": "Integrity constraints, normal forms"
    },
    {
      "fileName": "GATE_CS_1999.csv",
      "questionNumber": "20",
      "subject": null,
      "chapter": null,
      "subtopic": null
    },
    {
      "fileName": "GATE_CS_1999.csv",
      "questionNumber": "21",
      "subject": "Databases",
      "chapter": "Transactions",
      "subtopic": "Transactions and concurrency control"
    },
    {
      "fileName": "GATE_CS_1999.csv",
      "questionNumber": "22",
      "subject": "Engineering Mathematics",
      "chapter": "Probability and Statistics",
      "subtopic": "Conditional probability and Bayes theorem"
    },
    {
      "fileName": "GATE_CS_1999.csv",
      "questionNumber": "23",
      "subject": "Engineering Mathematics",
      "chapter": "Probability and Statistics",
      "subtopic": "Random Variables and Distributions"
    },
    {
      "fileName": "GATE_CS_1999.csv",
      "questionNumber": "24",
      "subject": "Engineering Mathematics",
      "chapter": "Discrete Mathematics",
      "subtopic": "Sets, Relations, and Functions"
    },
    {
      "fileName": "GATE_CS_1999.csv",
      "questionNumber": "25",
      "subject": "Engineering Mathematics",
      "chapter": "Discrete Mathematics",
      "subtopic": "Sets, Relations, and Functions"
    },
    {
      "fileName": "GATE_CS_1999.csv",
      "questionNumber": "26",
      "subject": "Engineering Mathematics",
      "chapter": "Discrete Mathematics",
      "subtopic": "Sets, Relations, and Functions"
    },
    {
      "fileName": "GATE_CS_1999.csv",
      "questionNumber": "27",
      "subject": "Digital Logic",
      "chapter": "Number Representations",
      "subtopic": "Number representations and computer arithmetic (fixed and floating point)."
    },
    {
      "fileName": "GATE_CS_1999.csv",
      "questionNumber": "28",
      "subject": "Digital Logic",
      "chapter": "Number Representations",
      "subtopic": "Number representations and computer arithmetic (fixed and floating point)."
    },
    {
      "fileName": "GATE_CS_1999.csv",
      "questionNumber": "29",
      "subject": "Digital Logic",
      "chapter": "Number Representations",
      "subtopic": "Number representations and computer arithmetic (fixed and floating point)."
    },
    {
      "fileName": "GATE_CS_1999.csv",
      "questionNumber": "30",
      "subject": "Digital Logic",
      "chapter": "Number Representations",
      "subtopic": "Number representations and computer arithmetic (fixed and floating point)."
    },
    {
      "fileName": "GATE_CS_1999.csv",
      "questionNumber": "31",
      "subject": "Digital Logic",
      "chapter": "Boolean Algebra",
      "subtopic": "Circuits: Combinational and sequential circuits."
    },
    {
      "fileName": "GATE_CS_1999.csv",
      "questionNumber": "32",
      "subject": "Digital Logic",
      "chapter": "Boolean Algebra",
      "subtopic": null
    },
    {
      "fileName": "GATE_CS_1999.csv",
      "questionNumber": "33",
      "subject": "Digital Logic",
      "chapter": "Boolean Algebra",
      "subtopic": null
    },
    {
      "fileName": "GATE_CS_1999.csv",
      "questionNumber": "34",
      "subject": "Digital Logic",
      "chapter": "Boolean Algebra",
      "subtopic": "Minimization"
    },
    {
      "fileName": "GATE_CS_1999.csv",
      "questionNumber": "35",
      "subject": "Theory of Computation",
      "chapter": "Formal Languages and Automata",
      "subtopic": "Regular expressions and finite automata"
    },
    {
      "fileName": "GATE_CS_1999.csv",
      "questionNumber": "36",
      "subject": "Theory of Computation",
      "chapter": "Language Properties",
      "subtopic": "Regular and context-free languages, pumping lemma"
    },
    {
      "fileName": "GATE_CS_1999.csv",
      "questionNumber": "37",
      "subject": "Theory of Computation",
      "chapter": "Formal Languages and Automata",
      "subtopic": "Context-free grammars and push-down automata"
    },
    {
      "fileName": "GATE_CS_1999.csv",
      "questionNumber": "38",
      "subject": "Theory of Computation",
      "chapter": "Language Properties",
      "subtopic": "Regular and context-free languages, pumping lemma"
    },
    {
      "fileName": "GATE_CS_1999.csv",
      "questionNumber": "39",
      "subject": "Theory of Computation",
      "chapter": "Language Properties",
      "subtopic": "Regular and context-free languages, pumping lemma"
    },
    {
      "fileName": "GATE_CS_1999.csv",
      "questionNumber": "40",
      "subject": "Theory of Computation",
      "chapter": "Language Properties",
      "subtopic": "Regular and context-free languages, pumping lemma"
    },
    {
      "fileName": "GATE_CS_1999.csv",
      "questionNumber": "41",
      "subject": "Engineering Mathematics",
      "chapter": "Calculus",
      "subtopic": null
    },
    {
      "fileName": "GATE_CS_1999.csv",
      "questionNumber": "42",
      "subject": "Engineering Mathematics",
      "chapter": "Discrete Mathematics",
      "subtopic": "Graph Theory: Connectivity, matching, colouring."
    },
    {
      "fileName": "GATE_CS_1999.csv",
      "questionNumber": "43",
      "subject": "Engineering Mathematics",
      "chapter": "Discrete Mathematics",
      "subtopic": "Combinatorics: Counting, recurrence relations, generating functions."
    },
    {
      "fileName": "GATE_CS_1999.csv",
      "questionNumber": "44",
      "subject": "Engineering Mathematics",
      "chapter": "Discrete Mathematics",
      "subtopic": "Combinatorics: Counting, recurrence relations, generating functions."
    },
    {
      "fileName": "GATE_CS_1999.csv",
      "questionNumber": "45",
      "subject": "Computer Organization and Architecture",
      "chapter": "Memory Hierarchy",
      "subtopic": "Cache, main memory and secondary storage"
    },
    {
      "fileName": "GATE_CS_1999.csv",
      "questionNumber": "46",
      "subject": "Computer Organization and Architecture",
      "chapter": "Instruction Set Architecture",
      "subtopic": "Machine instructions and addressing modes"
    },
    {
      "fileName": "GATE_CS_1999.csv",
      "questionNumber": "47",
      "subject": "Computer Organization and Architecture",
      "chapter": "Central Processing Unit (CPU)",
      "subtopic": "ALU, data-path and control unit"
    },
    {
      "fileName": "GATE_CS_1999.csv",
      "questionNumber": "48",
      "subject": "Computer Organization and Architecture",
      "chapter": "Instruction Set Architecture",
      "subtopic": "Machine instructions and addressing modes"
    },
    {
      "fileName": "GATE_CS_1999.csv",
      "questionNumber": "49",
      "subject": "Operating System",
      "chapter": "Scheduling",
      "subtopic": "CPU and I/O scheduling"
    },
    {
      "fileName": "GATE_CS_1999.csv",
      "questionNumber": "50",
      "subject": "Programming and Data Structures",
      "chapter": "Non-Linear Data Structures",
      "subtopic": "Trees, binary search trees, binary heaps, graphs"
    },
    {
      "fileName": "GATE_CS_1999.csv",
      "questionNumber": "51",
      "subject": "Databases",
      "chapter": "Data Models",
      "subtopic": "ER-model, Relational model: relational algebra, tuple calculus, SQL"
    },
    {
      "fileName": "GATE_CS_1999.csv",
      "questionNumber": "52",
      "subject": "Databases",
      "chapter": "File Organization and Indexing",
      "subtopic": "File organization, indexing (e.g., B and B+ trees)"
    },
    {
      "fileName": "GATE_CS_1999.csv",
      "questionNumber": "53",
      "subject": "Operating System",
      "chapter": "Concurrency",
      "subtopic": "Inter-process communication, concurrency and synchronization, Deadlock"
    },
    {
      "fileName": "GATE_CS_1999.csv",
      "questionNumber": "54",
      "subject": "Operating System",
      "chapter": "Memory Management",
      "subtopic": "Memory management and virtual memory"
    },
    {
      "fileName": "GATE_CS_1999.csv",
      "questionNumber": "55",
      "subject": "Computer Organization and Architecture",
      "chapter": "Memory Hierarchy",
      "subtopic": "Cache, main memory and secondary storage"
    },
    {
      "fileName": "GATE_CS_1999.csv",
      "questionNumber": "56",
      "subject": "Computer Organization and Architecture",
      "chapter": "Instruction Set Architecture",
      "subtopic": "Machine instructions and addressing modes"
    },
    {
      "fileName": "GATE_CS_1999.csv",
      "questionNumber": "57",
      "subject": "Compiler Design",
      "chapter": "Runtime Environments",
      "subtopic": null
    },
    {
      "fileName": "GATE_CS_1999.csv",
      "questionNumber": "58",
      "subject": "Compiler Design",
      "chapter": "Runtime Environments",
      "subtopic": null
    },
    {
      "fileName": "GATE_CS_1999.csv",
      "questionNumber": "59",
      "subject": "Engineering Mathematics",
      "chapter": "Discrete Mathematics",
      "subtopic": "Logic: Propositional and first order logic."
    },
    {
      "fileName": "GATE_CS_1999.csv",
      "questionNumber": "60",
      "subject": "Computer Organization and Architecture",
      "chapter": "Pipelining",
      "subtopic": "Instruction pipelining, pipeline hazards"
    },
    {
      "fileName": "GATE_CS_1999.csv",
      "questionNumber": "61",
      "subject": "Algorithms",
      "chapter": "Complexity Analysis",
      "subtopic": "Asymptotic worst case time and space complexity"
    },
    {
      "fileName": "GATE_CS_1999.csv",
      "questionNumber": "62",
      "subject": "Theory of Computation",
      "chapter": "Computability",
      "subtopic": "Turing machines and undecidability"
    },
    {
      "fileName": "GATE_CS_1999.csv",
      "questionNumber": "63",
      "subject": "Algorithms",
      "chapter": "Basic Techniques",
      "subtopic": "Searching, sorting, hashing"
    },
    {
      "fileName": "GATE_CS_1999.csv",
      "questionNumber": "64",
      "subject": "Algorithms",
      "chapter": "Complexity Analysis",
      "subtopic": "Asymptotic worst case time and space complexity"
    },
    {
      "fileName": "GATE_CS_1999.csv",
      "questionNumber": "65",
      "subject": "Engineering Mathematics",
      "chapter": "Discrete Mathematics",
      "subtopic": "Graph Theory: Connectivity, matching, colouring."
    },
    {
      "fileName": "GATE_CS_1999.csv",
      "questionNumber": "66",
      "subject": "Engineering Mathematics",
      "chapter": "Discrete Mathematics",
      "subtopic": "Algebraic Structures: Monoids, Groups."
    }
  ]